nebula_watcher/__init__.py
nebula_watcher/nebula_watcher.py
nebula_watcher/diagram_resources/cve.png
nebula_watcher/diagram_resources/ethical_hacker.png
nebula_watcher/diagram_resources/ip.png
nebula_watcher/diagram_resources/port.png
nebula_watcher/diagram_resources/service.png
nebula_watcher-0.4.dist-info/LICENSE
nebula_watcher-0.4.dist-info/METADATA
nebula_watcher-0.4.dist-info/WHEEL
nebula_watcher-0.4.dist-info/entry_points.txt
nebula_watcher-0.4.dist-info/top_level.txt
nebula_watcher-0.4.dist-info/RECORD
