Metadata-Version: 2.1
Name: nebula-watcher
Version: 0.4
Summary: A tool to monitor the IP addresses and ports you have engaged with during a penetration test using the Nebula-Watcher tool
Home-page: https://github.com/berylliumsec/nebula_watcher
Author: David I
Author-email: david@berylliumsec.com
Classifier: Programming Language :: Python :: 3
Classifier: License :: OSI Approved :: MIT License
Classifier: Operating System :: OS Independent
License-File: LICENSE
Requires-Dist: diagrams
Requires-Dist: psutil
